anxcor/__init__.py
anxcor/abstractions.py
anxcor/anxcor_utils.py
anxcor/containers.py
anxcor/core.py
anxcor/filters.py
anxcor/numpyfftfilter.py
anxcor/utils.py
anxcor/xarray_routines.py
anxcor-0.1.0.dist-info/LICENSE
anxcor-0.1.0.dist-info/METADATA
anxcor-0.1.0.dist-info/WHEEL
anxcor-0.1.0.dist-info/top_level.txt
anxcor-0.1.0.dist-info/RECORD
