Metadata-Version: 2.1
Name: anxcor
Version: 0.1.0
Summary: ANXCOR is a python library for performing seismic ambient noise crosscorrelations
Home-page: https://github.com/uofuseismo/anxcor
Author: Kevin A. Mendoza
Author-email: kevin.mendoza@utah.edu
License: MIT
Platform: UNKNOWN
Classifier: Development Status :: 3 - Alpha
Classifier: Intended Audience :: Science/Research
Classifier: Programming Language :: Python
Classifier: Programming Language :: Python :: 3
Classifier: Programming Language :: Python :: 3.6
Classifier: Programming Language :: Python :: 3.7
Classifier: License :: OSI Approved :: MIT License
Classifier: Operating System :: OS Independent
Classifier: Topic :: Scientific/Engineering
Requires-Dist: obspy (>=1.1)
Requires-Dist: xarray (>=0.14)
Requires-Dist: numpy (>=1.17)
Requires-Dist: scipy (>=1.0)
Requires-Dist: pandas (>=0.25)
Requires-Dist: sparse (>=0.8)
Requires-Dist: bottleneck (>=1.2)
Requires-Dist: pympler (>=0.7)
